[
  {
    "idgp": "120363304815961499@g.us",
    "ids": [
      {
        "id": "556198779578@s.whatsapp.net",
        "tempo": 1729877245
      },
      {
        "id": "558291074662@s.whatsapp.net",
        "tempo": 1728326877
      },
      {
        "id": "554599140881@s.whatsapp.net",
        "tempo": 1727926268
      },
      {
        "id": "557582796961@s.whatsapp.net",
        "tempo": 1727993152
      },
      {
        "id": "557182463419@s.whatsapp.net",
        "tempo": 1727789134
      },
      {
        "id": "5515998094557@s.whatsapp.net",
        "tempo": 1727783815
      },
      {
        "id": "554591188725@s.whatsapp.net",
        "tempo": 1728335535
      },
      {
        "id": "5517991921451@s.whatsapp.net",
        "tempo": 1727930929
      },
      {
        "id": "5519982563921@s.whatsapp.net",
        "tempo": 1729793921
      },
      {
        "id": "554888476794@s.whatsapp.net",
        "tempo": 1728305813
      },
      {
        "id": "5521973194243@s.whatsapp.net",
        "tempo": 1728322174
      },
      {
        "id": "5511953688349@s.whatsapp.net",
        "tempo": 1729812170
      },
      {
        "id": "559292559024@s.whatsapp.net",
        "tempo": 1729879600
      },
      {
        "id": "557799159834@s.whatsapp.net",
        "tempo": 1729706860
      },
      {
        "id": "559884282313@s.whatsapp.net",
        "tempo": 1729812055
      }
    ]
  },
  {
    "idgp": "120363289973153215@g.us",
    "ids": [
      {
        "id": "558194870488@s.whatsapp.net",
        "tempo": 1733260302
      },
      {
        "id": "557592058907@s.whatsapp.net",
        "tempo": 1733249789
      },
      {
        "id": "554396347902@s.whatsapp.net",
        "tempo": 1733236459
      },
      {
        "id": "559188515596@s.whatsapp.net",
        "tempo": 1733221362
      },
      {
        "id": "558681722637@s.whatsapp.net",
        "tempo": 1733221481
      },
      {
        "id": "553171493301@s.whatsapp.net",
        "tempo": 1733258135
      }
    ]
  },
  {
    "idgp": "120363386013307765@g.us",
    "ids": [
      {
        "id": "554892112991@s.whatsapp.net",
        "tempo": 1743523880
      },
      {
        "id": "557981076965@s.whatsapp.net",
        "tempo": 1745359807
      },
      {
        "id": "557187926731@s.whatsapp.net",
        "tempo": 1743455333
      },
      {
        "id": "559392397154@s.whatsapp.net",
        "tempo": 1743785155
      },
      {
        "id": "558594221962@s.whatsapp.net",
        "tempo": 1743871286
      },
      {
        "id": "5522999138982@s.whatsapp.net",
        "tempo": 1747412423
      },
      {
        "id": "558173456701@s.whatsapp.net",
        "tempo": 1744146760
      },
      {
        "id": "5513981634104@s.whatsapp.net",
        "tempo": 1743440467
      },
      {
        "id": "5521979205000@s.whatsapp.net",
        "tempo": 1743455851
      },
      {
        "id": "559881135740@s.whatsapp.net",
        "tempo": 1744413642
      },
      {
        "id": "351910179688@s.whatsapp.net",
        "tempo": 1745354001
      },
      {
        "id": "554499933741@s.whatsapp.net",
        "tempo": 1745371150
      },
      {
        "id": "554484160399@s.whatsapp.net",
        "tempo": 1745371248
      },
      {
        "id": "558391688572@s.whatsapp.net",
        "tempo": 1745371199
      },
      {
        "id": "559192757550@s.whatsapp.net",
        "tempo": 1746151312
      },
      {
        "id": "559291086326@s.whatsapp.net",
        "tempo": 1747313581
      },
      {
        "id": "5512974090637@s.whatsapp.net",
        "tempo": 1745945957
      },
      {
        "id": "5512988777980@s.whatsapp.net",
        "tempo": 1745946160
      },
      {
        "id": "5517981094216@s.whatsapp.net",
        "tempo": 1746126760
      },
      {
        "id": "5514998108033@s.whatsapp.net",
        "tempo": 1746981598
      },
      {
        "id": "559284602840@s.whatsapp.net",
        "tempo": 1747412583
      },
      {
        "id": "5511944875813@s.whatsapp.net",
        "tempo": 1747422035
      },
      {
        "id": "559491302565@s.whatsapp.net",
        "tempo": 1747605509
      },
      {
        "id": "559293546826@s.whatsapp.net",
        "tempo": 1748116444
      },
      {
        "id": "5528992779159@s.whatsapp.net",
        "tempo": 1748129568
      }
    ]
  }
]